CHANGES.rst
LICENSE
MANIFEST.in
README.rst
openerp_sane.py
setup.py
openerp_sane.egg-info/PKG-INFO
openerp_sane.egg-info/SOURCES.txt
openerp_sane.egg-info/dependency_links.txt
openerp_sane.egg-info/top_level.txt