Metadata-Version: 1.0
Name: openerp-sane
Version: 0.2
Summary: Small utilities to ease OpenERP development
Home-page: https://github.com/savoirfairelinux/openerp-sane
Author: Savoir-faire Linux
Author-email: virgil.dupras@savoirfairelinux.com
License: AGPL
Platform: UNKNOWN
